rectangle_packing_solver/__init__.py
rectangle_packing_solver/__version__.py
rectangle_packing_solver/floorplan.py
rectangle_packing_solver/problem.py
rectangle_packing_solver/sequence_pair.py
rectangle_packing_solver/solution.py
rectangle_packing_solver/solver.py
rectangle_packing_solver/visualizer.py
tests/__init__.py
tests/example_data.py
tests/test_floorplan.py
tests/test_problem.py
tests/test_sequence_pair.py
tests/test_solution.py
tests/test_solver.py
tests/test_version.py
tests/test_visualizer.py
rectangle_packing_solver-0.0.5.dist-info/LICENSE
rectangle_packing_solver-0.0.5.dist-info/METADATA
rectangle_packing_solver-0.0.5.dist-info/WHEEL
rectangle_packing_solver-0.0.5.dist-info/top_level.txt
rectangle_packing_solver-0.0.5.dist-info/RECORD
