Metadata-Version: 2.1
Name: rectangle-packing-solver
Version: 0.0.5
Summary: A solver to find a solution of the 2D rectangle packing problem by simulated annealing (SA) optimization.
Home-page: https://github.com/kotarot/rectangle-packing-solver
Author: Kotaro Terada
Author-email: kotarot@apache.org
License: Apache 2.0
Keywords: python rectangle-packing placement floorplan solver optimization simulated-annealing sequence-pair
Platform: UNKNOWN
Classifier: Development Status :: 4 - Beta
Classifier: Intended Audience :: Developers
Classifier: Intended Audience :: End Users/Desktop
Classifier: License :: OSI Approved :: Apache Software License
Classifier: Programming Language :: Python :: 3.7
Classifier: Programming Language :: Python :: 3.8
Classifier: Programming Language :: Python :: 3.9
Requires-Dist: simanneal (<1.0.0,>=0.5.0)
Requires-Dist: matplotlib (<4.0.0,>=3.3.4)
Requires-Dist: tqdm (<5.0.0,>=4.62.3)
Requires-Dist: graphlib-backport (<2.0.0,>=1.0.3)
Provides-Extra: dev
Requires-Dist: pytest (<7.0.0,>=6.2.4) ; extra == 'dev'
Requires-Dist: pytest-cov (<3.0.0,>=2.11.1) ; extra == 'dev'
Requires-Dist: black (<22.0,>=21.5b0) ; extra == 'dev'
Requires-Dist: isort (<6.0.0,>=5.8.0) ; extra == 'dev'
Requires-Dist: flake8 (<4.0.0,>=3.9.1) ; extra == 'dev'
Requires-Dist: flake8-bugbear (<22.0.0,>=21.9.2) ; extra == 'dev'
Requires-Dist: mypy (<1.0,>=0.812) ; extra == 'dev'
